{
  "lastUpdated": "2026-05-15T07:41:49.001Z",
  "metals": {
    "ALLOY": {
      "metalName": "ALLOY",
      "history": [
        {
          "purity": 100,
          "rate": 6000,
          "createdTime": "2026-05-15 10:55:05",
          "ratediff": 0
        }
      ],
      "price": 6000,
      "ratediff": 0,
      "bollinger": {
        "middle": 6000,
        "upper": 6000,
        "lower": 6000
      },
      "volatility": 0,
      "drawdown": 0,
      "anomalyScore": null,
      "chartData": {
        "labels": [
          "2026-04-18",
          "2026-04-20",
          "2026-04-22",
          "2026-04-23",
          "2026-04-23",
          "2026-04-24",
          "2026-04-25",
          "2026-04-27",
          "2026-04-28",
          "2026-04-28",
          "2026-04-29",
          "2026-04-29",
          "2026-04-30",
          "2026-04-30",
          "2026-05-02",
          "2026-05-04",
          "2026-05-04",
          "2026-05-05",
          "2026-05-06",
          "2026-05-07",
          "2026-05-07",
          "2026-05-08",
          "2026-05-09",
          "2026-05-11",
          "2026-05-11",
          "2026-05-12",
          "2026-05-13",
          "2026-05-13",
          "2026-05-14",
          "2026-05-15"
        ],
        "values": [
          6000,
          6000,
          6000,
          6000,
          6000,
          6000,
          6000,
          6000,
          6000,
          6000,
          6000,
          6000,
          6000,
          6000,
          6000,
          6000,
          6000,
          6000,
          6000,
          6000,
          6000,
          6000,
          6000,
          6000,
          6000,
          6000,
          6000,
          6000,
          6000,
          6000
        ],
        "ma7": [
          null,
          null,
          null,
          null,
          null,
          null,
          6000,
          6000,
          6000,
          6000,
          6000,
          6000,
          6000,
          6000,
          6000,
          6000,
          6000,
          6000,
          6000,
          6000,
          6000,
          6000,
          6000,
          6000,
          6000,
          6000,
          6000,
          6000,
          6000,
          6000
        ]
      },
      "ma7": 6000
    },
    "GOLD": {
      "metalName": "GOLD",
      "history": [
        {
          "purity": 6,
          "rate": 16459,
          "createdTime": "2026-05-15 10:55:05",
          "ratediff": -199
        },
        {
          "purity": 37.5,
          "rate": 6086,
          "createdTime": "2026-05-15 10:55:05",
          "ratediff": -53
        },
        {
          "purity": 58.3,
          "rate": 9467,
          "createdTime": "2026-05-15 10:55:05",
          "ratediff": -82
        },
        {
          "purity": 58.5,
          "rate": 9467,
          "createdTime": "2026-05-15 10:55:05",
          "ratediff": -82
        },
        {
          "purity": 75,
          "rate": 12172,
          "createdTime": "2026-05-15 10:55:05",
          "ratediff": -105
        },
        {
          "purity": 91.6,
          "rate": 14667,
          "createdTime": "2026-05-15 10:55:05",
          "ratediff": -126
        },
        {
          "purity": 99.5,
          "rate": 16000,
          "createdTime": "2026-05-15 10:55:05",
          "ratediff": -138
        },
        {
          "purity": 100,
          "rate": 16000,
          "createdTime": "2026-05-15 10:55:05",
          "ratediff": -138
        }
      ],
      "price": 16000,
      "ratediff": -138,
      "bollinger": {
        "middle": 15388.9,
        "upper": 16336.11421019746,
        "lower": 14441.68578980254
      },
      "volatility": 0.3049671050715,
      "drawdown": 4.69382892542292,
      "anomalyScore": 2.7694278928295715,
      "chartData": {
        "labels": [
          "2026-04-18",
          "2026-04-20",
          "2026-04-22",
          "2026-04-23",
          "2026-04-23",
          "2026-04-24",
          "2026-04-25",
          "2026-04-27",
          "2026-04-28",
          "2026-04-28",
          "2026-04-29",
          "2026-04-29",
          "2026-04-30",
          "2026-04-30",
          "2026-05-02",
          "2026-05-04",
          "2026-05-04",
          "2026-05-05",
          "2026-05-06",
          "2026-05-07",
          "2026-05-07",
          "2026-05-08",
          "2026-05-09",
          "2026-05-11",
          "2026-05-11",
          "2026-05-12",
          "2026-05-13",
          "2026-05-13",
          "2026-05-14",
          "2026-05-15"
        ],
        "values": [
          15580,
          15530,
          15470,
          15350,
          15430,
          15295,
          15400,
          15440,
          15295,
          15085,
          15135,
          15040,
          15055,
          15270,
          15085,
          15085,
          14960,
          14911,
          15205,
          15244,
          15295,
          15264,
          15235,
          15205,
          15343,
          15392,
          16788,
          16128,
          16138,
          16000
        ],
        "ma7": [
          null,
          null,
          null,
          null,
          null,
          null,
          15436.42857142857,
          15416.42857142857,
          15382.857142857143,
          15327.857142857143,
          15297.142857142857,
          15241.42857142857,
          15207.142857142857,
          15188.57142857143,
          15137.857142857143,
          15107.857142857143,
          15090,
          15058,
          15081.57142857143,
          15108.57142857143,
          15112.142857142857,
          15137.714285714286,
          15159.142857142857,
          15194.142857142857,
          15255.857142857143,
          15282.57142857143,
          15503.142857142857,
          15622.142857142857,
          15747,
          15856.285714285714
        ]
      },
      "ma7": 15856.285714285714,
      "chartData916": {
        "labels": [
          "2026-04-18",
          "2026-04-20",
          "2026-04-22",
          "2026-04-23",
          "2026-04-23",
          "2026-04-24",
          "2026-04-25",
          "2026-04-27",
          "2026-04-28",
          "2026-04-28",
          "2026-04-29",
          "2026-04-29",
          "2026-04-30",
          "2026-04-30",
          "2026-05-02",
          "2026-05-04",
          "2026-05-04",
          "2026-05-05",
          "2026-05-06",
          "2026-05-07",
          "2026-05-07",
          "2026-05-08",
          "2026-05-09",
          "2026-05-11",
          "2026-05-11",
          "2026-05-12",
          "2026-05-13",
          "2026-05-13",
          "2026-05-14",
          "2026-05-15"
        ],
        "values": [
          14280,
          14235,
          14181,
          14073,
          14145,
          14019,
          14118,
          14154,
          14019,
          13830,
          13875,
          13785,
          13803,
          14000,
          13830,
          13830,
          13713,
          13668,
          13938,
          13974,
          14019,
          13992,
          13965,
          13938,
          14064,
          14109,
          15387,
          14784,
          14793,
          14667
        ]
      },
      "chartData100": {
        "labels": [
          "2026-04-18",
          "2026-04-20",
          "2026-04-22",
          "2026-04-23",
          "2026-04-23",
          "2026-04-24",
          "2026-04-25",
          "2026-04-27",
          "2026-04-28",
          "2026-04-28",
          "2026-04-29",
          "2026-04-29",
          "2026-04-30",
          "2026-04-30",
          "2026-05-02",
          "2026-05-04",
          "2026-05-04",
          "2026-05-05",
          "2026-05-06",
          "2026-05-07",
          "2026-05-07",
          "2026-05-08",
          "2026-05-09",
          "2026-05-11",
          "2026-05-11",
          "2026-05-12",
          "2026-05-13",
          "2026-05-13",
          "2026-05-14",
          "2026-05-15"
        ],
        "values": [
          15580,
          15530,
          15470,
          15350,
          15430,
          15295,
          15400,
          15440,
          15295,
          15085,
          15135,
          15040,
          15055,
          15270,
          15085,
          15085,
          14960,
          14911,
          15205,
          15244,
          15295,
          15264,
          15235,
          15205,
          15343,
          15392,
          16788,
          16128,
          16138,
          16000
        ]
      },
      "ratediff916": -126,
      "ratediff100": -138
    },
    "PLATINUM": {
      "metalName": "PLATINUM",
      "history": [
        {
          "purity": 95,
          "rate": 8627,
          "createdTime": "2026-05-15 10:55:05",
          "ratediff": 0
        },
        {
          "purity": 100,
          "rate": 8627,
          "createdTime": "2026-05-15 10:55:05",
          "ratediff": 0
        }
      ],
      "price": 8627,
      "ratediff": 0,
      "bollinger": {
        "middle": 7614.5,
        "upper": 8426.281867252528,
        "lower": 6802.718132747473
      },
      "volatility": 0.3586249045474389,
      "drawdown": 8.275238832946037,
      "anomalyScore": 6.807121140062682,
      "chartData": {
        "labels": [
          "2026-04-18",
          "2026-04-20",
          "2026-04-22",
          "2026-04-23",
          "2026-04-23",
          "2026-04-24",
          "2026-04-25",
          "2026-04-27",
          "2026-04-28",
          "2026-04-28",
          "2026-04-29",
          "2026-04-29",
          "2026-04-30",
          "2026-04-30",
          "2026-05-02",
          "2026-05-04",
          "2026-05-04",
          "2026-05-05",
          "2026-05-06",
          "2026-05-07",
          "2026-05-07",
          "2026-05-08",
          "2026-05-09",
          "2026-05-11",
          "2026-05-11",
          "2026-05-12",
          "2026-05-13",
          "2026-05-13",
          "2026-05-14",
          "2026-05-15"
        ],
        "values": [
          7746,
          7641,
          7615,
          7632,
          7632,
          7632,
          7484,
          7457,
          7489,
          7489,
          7377,
          7377,
          7226,
          7226,
          7105,
          7105,
          7481,
          7425,
          7473,
          7473,
          7652,
          7652,
          7712,
          7470,
          7766,
          7766,
          7842,
          7908,
          8627,
          8627
        ],
        "ma7": [
          null,
          null,
          null,
          null,
          null,
          null,
          7626,
          7584.714285714285,
          7563,
          7545,
          7508.571428571428,
          7472.142857142857,
          7414.142857142857,
          7377.285714285715,
          7327,
          7272.142857142857,
          7271,
          7277.857142857143,
          7291.571428571428,
          7326.857142857143,
          7387.714285714285,
          7465.857142857143,
          7552.571428571428,
          7551,
          7599.714285714285,
          7641.571428571428,
          7694.285714285715,
          7730.857142857143,
          7870.142857142857,
          8000.857142857143
        ]
      },
      "ma7": 8000.857142857143
    },
    "SILVER": {
      "metalName": "SILVER",
      "history": [
        {
          "purity": 40,
          "rate": 288.9,
          "createdTime": "2026-05-15 10:55:05",
          "ratediff": -11
        },
        {
          "purity": 45,
          "rate": 288.9,
          "createdTime": "2026-05-15 10:55:05",
          "ratediff": -11
        },
        {
          "purity": 50,
          "rate": 288.9,
          "createdTime": "2026-05-15 10:55:05",
          "ratediff": -11
        },
        {
          "purity": 55,
          "rate": 288.9,
          "createdTime": "2026-05-15 10:55:05",
          "ratediff": -11
        },
        {
          "purity": 60,
          "rate": 288.9,
          "createdTime": "2026-05-15 10:55:05",
          "ratediff": -11
        },
        {
          "purity": 65,
          "rate": 288.9,
          "createdTime": "2026-05-15 10:55:05",
          "ratediff": -11
        },
        {
          "purity": 70,
          "rate": 288.9,
          "createdTime": "2026-05-15 10:55:05",
          "ratediff": -11
        },
        {
          "purity": 75,
          "rate": 288.9,
          "createdTime": "2026-05-15 10:55:05",
          "ratediff": -11
        },
        {
          "purity": 80,
          "rate": 288.9,
          "createdTime": "2026-05-15 10:55:05",
          "ratediff": -11
        },
        {
          "purity": 92.5,
          "rate": 288.9,
          "createdTime": "2026-05-15 10:55:05",
          "ratediff": -11
        },
        {
          "purity": 99.9,
          "rate": 288.9,
          "createdTime": "2026-05-15 10:55:05",
          "ratediff": -11
        },
        {
          "purity": 100,
          "rate": 288.9,
          "createdTime": "2026-05-15 10:55:05",
          "ratediff": -11
        }
      ],
      "price": 288.9,
      "ratediff": -11,
      "bollinger": {
        "middle": 270.65500000000003,
        "upper": 313.38487128461776,
        "lower": 227.92512871538227
      },
      "volatility": 0.4759275029541377,
      "drawdown": 9.746954076850997,
      "anomalyScore": 2.0269219101578155,
      "chartData": {
        "labels": [
          "2026-04-18",
          "2026-04-20",
          "2026-04-22",
          "2026-04-23",
          "2026-04-23",
          "2026-04-24",
          "2026-04-25",
          "2026-04-27",
          "2026-04-28",
          "2026-04-28",
          "2026-04-29",
          "2026-04-29",
          "2026-04-30",
          "2026-04-30",
          "2026-05-02",
          "2026-05-04",
          "2026-05-04",
          "2026-05-05",
          "2026-05-06",
          "2026-05-07",
          "2026-05-07",
          "2026-05-08",
          "2026-05-09",
          "2026-05-11",
          "2026-05-11",
          "2026-05-12",
          "2026-05-13",
          "2026-05-13",
          "2026-05-14",
          "2026-05-15"
        ],
        "values": [
          266.9,
          262.9,
          259.9,
          255.9,
          255.9,
          252.9,
          256.9,
          256.9,
          252.9,
          252.9,
          251.9,
          251.9,
          246.9,
          251.9,
          257.9,
          257.9,
          251.9,
          253.1,
          261.9,
          262.9,
          267.9,
          266.1,
          268.5,
          269.1,
          279.9,
          284.4,
          320.1,
          320.1,
          299.9,
          288.9
        ],
        "ma7": [
          null,
          null,
          null,
          null,
          null,
          null,
          258.75714285714287,
          257.3285714285715,
          255.90000000000003,
          254.90000000000003,
          254.32857142857145,
          253.7571428571429,
          252.90000000000003,
          252.1857142857143,
          252.32857142857145,
          253.04285714285717,
          252.90000000000003,
          253.07142857142858,
          254.5,
          256.7857142857143,
          259.07142857142856,
          260.24285714285713,
          261.7571428571428,
          264.2142857142857,
          268.04285714285714,
          271.25714285714287,
          279.42857142857144,
          286.88571428571424,
          291.7142857142857,
          294.62857142857143
        ]
      },
      "ma7": 294.62857142857143
    }
  }
}